{"name":"Login with invalid password","testSteps":[{"number":1,"description":"Given Go to the login Skype page successfully","duration":3724,"startTime":1465972932557,"screenshots":[{"screenshot":"8e097353c8dfe833f552fe4e0746a971.png"},{"screenshot":"a3f75d61ee9f4103180ce1cf49601b4e.png"}],"result":"SUCCESS","children":[{"number":2,"description":"Open  skype login","duration":3537,"startTime":1465972932660,"screenshots":[{"screenshot":"8e097353c8dfe833f552fe4e0746a971.png"},{"screenshot":"a3f75d61ee9f4103180ce1cf49601b4e.png"}],"result":"SUCCESS"}]},{"number":3,"description":"When Input a skype name \"Lamngoc_xinhxinh\"","duration":998,"startTime":1465972936282,"screenshots":[{"screenshot":"23341f4858ad6587f0d327f39ef9f652.png"}],"result":"SUCCESS"},{"number":4,"description":"And Input a password \"1234567890\"","duration":813,"startTime":1465972937280,"screenshots":[{"screenshot":"346e3480a790b26292f295473603371c.png"}],"result":"SUCCESS"},{"number":5,"description":"And Click Sign in button","duration":2289,"startTime":1465972938094,"screenshots":[{"screenshot":"65671eff356ef12397ce0f6882d16cd1.png"}],"result":"SUCCESS"},{"number":6,"description":"Then Show an error message \"Signing in failed. Please double-check your Skype Name and re-enter your password.\"","duration":549,"startTime":1465972940384,"screenshots":[{"screenshot":"65671eff356ef12397ce0f6882d16cd1.png"}],"result":"SUCCESS"}],"userStory":{"id":"login-skype-page","storyName":"Login Skype page","path":"Login_skype.feature","narrative":"I want to test three cases:\r\nLogin with invalid Skype name\r\nLogin with invalid password\r\nLogin with invalid Skype name and password","type":"feature"},"title":"Login with invalid password","description":"","tags":[{"name":"Login Skype page","type":"feature"}],"startTime":1465972932553,"duration":8381,"sessionId":"c7d434ef-e438-41f7-ad34-315826fa5bb4","driver":"firefox","manual":false,"result":"SUCCESS"}